Metadata-Version: 2.1
Name: deepeval-no-telemetry
Version: 2.4.9a0
Summary: The LLM Evaluation Framework
Home-page: https://github.com/88roy88/deepeval-no-telemetry
License: Apache-2.0
Author: Jeffrey Ip
Author-email: jeffreyip@confident-ai.com
Requires-Python: >=3.9,<4.0
Classifier: License :: OSI Approved :: Apache Software License
Classifier: Programming Language :: Python :: 3
Classifier: Programming Language :: Python :: 3.9
Classifier: Programming Language :: Python :: 3.10
Classifier: Programming Language :: Python :: 3.11
Classifier: Programming Language :: Python :: 3.12
Requires-Dist: aiohttp
Requires-Dist: datasets
Requires-Dist: docx2txt (>=0.8,<0.9)
Requires-Dist: importlib-metadata (>=6.0.2)
Requires-Dist: instructor
Requires-Dist: langchain
Requires-Dist: langchain-core
Requires-Dist: langchain_community
Requires-Dist: langchain_openai
Requires-Dist: llama-index
Requires-Dist: llama-index-llms-langchain
Requires-Dist: ollama
Requires-Dist: openai
Requires-Dist: portalocker
Requires-Dist: protobuf
Requires-Dist: requests (>=2.31.0,<3.0.0)
Requires-Dist: rich (>=13.6.0,<14.0.0)
Requires-Dist: tabulate (>=0.9.0,<0.10.0)
Requires-Dist: tenacity (<=9.0.0)
Requires-Dist: tqdm (>=4.66.1,<5.0.0)
Requires-Dist: typer
Project-URL: Documentation, https://docs.confident-ai.com
Project-URL: Repository, https://github.com/88roy88/deepeval-no-telemetry
